pilecap/__init__.py
pilecap/__main__.py
pilecap/_cli.py
pilecap/_compilation.py
pilecap/_env.py
pilecap/_gathering.py
pilecap/_misc.py
pilecap/_typing.py
pilecap/_version.py
pilecap/py.typed
pilecap-0.3.dist-info/LICENSE
pilecap-0.3.dist-info/METADATA
pilecap-0.3.dist-info/WHEEL
pilecap-0.3.dist-info/entry_points.txt
pilecap-0.3.dist-info/top_level.txt
pilecap-0.3.dist-info/RECORD
