Metadata-Version: 2.1
Name: pilecap
Version: 0.3
Summary: A stable foundation for reproducible builds
Home-page: https://github.com/apljungquist/pilecap
License: MIT
Classifier: License :: OSI Approved :: MIT License
Classifier: Programming Language :: Python :: 3
License-File: LICENSE
Requires-Dist: build
Requires-Dist: pep517
Requires-Dist: pip-tools
